bchydro/__init__.py
bchydro/api.py
bchydro/const.py
bchydro/exceptions.py
bchydro/types.py
bchydro-0.8.1.dist-info/LICENSE.txt
bchydro-0.8.1.dist-info/METADATA
bchydro-0.8.1.dist-info/WHEEL
bchydro-0.8.1.dist-info/top_level.txt
bchydro-0.8.1.dist-info/RECORD
