Metadata-Version: 2.1
Name: bchydro
Version: 0.8.1
Summary: BCHydro API
Home-page: https://github.com/emcniece/bchydro
Author: Eric McNiece
Author-email: emcniece@gmail.com
License: MIT
Download-URL: https://github.com/emcniece/bchydro/releases/latest/download/package.tar.gz
Keywords: bchydro
Platform: UNKNOWN
Classifier: Development Status :: 3 - Alpha
Classifier: Intended Audience :: Developers
Classifier: Topic :: Software Development :: Build Tools
Classifier: License :: OSI Approved :: MIT License
Classifier: Programming Language :: Python :: 3
Classifier: Programming Language :: Python :: 3.8
Requires-Dist: aiohttp (<=3.7.3)
Requires-Dist: beautifulsoup4 (<=4.9.3)
Requires-Dist: tenacity (<=6.3.1)
Requires-Dist: ratelimit (<=2.2.1)
